README.md
setup.py
snipeit/Accessories.py
snipeit/Assets.py
snipeit/Categories.py
snipeit/Company.py
snipeit/Components.py
snipeit/Consumables.py
snipeit/Fieldsets.py
snipeit/Licenses.py
snipeit/Locations.py
snipeit/Maintenances.py
snipeit/Manufacturers.py
snipeit/Models.py
snipeit/StatusLabels.py
snipeit/Users.py
snipeit/__init__.py
snipeit.egg-info/PKG-INFO
snipeit.egg-info/SOURCES.txt
snipeit.egg-info/dependency_links.txt
snipeit.egg-info/not-zip-safe
snipeit.egg-info/requires.txt
snipeit.egg-info/top_level.txt