Metadata-Version: 2.1
Name: snipeit
Version: 1.0
Summary: Python library to access the SnipeIT API
Home-page: https://github.com/jbloomer/SnipeIT-PythonAPI
Author: Jared Bloomer (Cox Automotive Inc.)
Author-email: jared.bloomer@coxautoinc.com
License: MIT
Platform: UNKNOWN
